epicbox/__init__.py
epicbox/config.py
epicbox/exceptions.py
epicbox/sandboxes.py
epicbox/utils.py
epicbox-1.0.0.dist-info/LICENSE
epicbox-1.0.0.dist-info/WHEEL
epicbox-1.0.0.dist-info/METADATA
epicbox-1.0.0.dist-info/RECORD
