Metadata-Version: 2.1
Name: epicbox
Version: 1.0.0
Summary: Run untrusted code in secure Docker based sandboxes
Home-page: https://github.com/StepicOrg/epicbox
License: MIT
Keywords: docker,sandbox
Author: Pavel Sviderski
Author-email: ps@stepik.org
Requires-Python: >=3.4,<4.0
Classifier: License :: OSI Approved :: MIT License
Classifier: Programming Language :: Python :: 3
Classifier: Programming Language :: Python :: 3.4
Classifier: Programming Language :: Python :: 3.5
Classifier: Programming Language :: Python :: 3.6
Classifier: Programming Language :: Python :: 3.7
Classifier: Topic :: Software Development :: Libraries :: Python Modules
Requires-Dist: docker (>=2)
Requires-Dist: python-dateutil (>=2.4,<3.0)
Requires-Dist: requests (>=2.14.2,<3.0.0)
Requires-Dist: structlog (>=15.3)
